sdhpy/__init__.py
sdhpy/errors.py
sdhpy/pandas.py
sdhpy/errors/__init__.py
sdhpy/errors/errors.py
sdhpy/sdhstore/__init__.py
sdhpy/sdhstore/ckanhelper.py
sdhpy/sdhtoolkit/__init__.py
sdhpy/sdhtoolkit/dataset.py
sdhpy/sdhtoolkit/serving.py
sdhpy/tests/__init__.py
sdhpy/tests/numpy_tests.py
sdhpy/tests/pandas_tests.py
sdhpy/utils/__init__.py
sdhpy/utils/utils.py
sdhpy-0.3.dist-info/DESCRIPTION.rst
sdhpy-0.3.dist-info/METADATA
sdhpy-0.3.dist-info/RECORD
sdhpy-0.3.dist-info/WHEEL
sdhpy-0.3.dist-info/metadata.json
sdhpy-0.3.dist-info/top_level.txt
